appifier/__init__.py
appifier/__main__.py
appifier-0.1.0.dist-info/LICENSE
appifier-0.1.0.dist-info/METADATA
appifier-0.1.0.dist-info/WHEEL
appifier-0.1.0.dist-info/entry_points.txt
appifier-0.1.0.dist-info/top_level.txt
appifier-0.1.0.dist-info/RECORD
