Metadata-Version: 2.1
Name: appifier
Version: 0.1.0
Summary: A utility to search for .desktop files and create desktop entries.
Home-page: https://github.com/rohittp0/Appify
Author: Rohit T P
Author-email: tprohit9@gmail.com
License: UNKNOWN
Platform: UNKNOWN
Classifier: Programming Language :: Python :: 3
Classifier: License :: OSI Approved :: GNU Affero General Public License v3
Classifier: Environment :: Console
Classifier: Intended Audience :: End Users/Desktop
Classifier: Natural Language :: English
Classifier: Operating System :: POSIX :: Linux
Classifier: Topic :: Utilities
Requires-Python: >=3.6
Requires-Dist: enquiries
